{
  "hash": "983ebe7270825f72b1a8b94a07d6a653",
  "result": {
    "markdown": "---\ntitle: \"Currilum vitae\"\nformat:\n  html:\n    toc: true\n  pdf:\n    author: Nicholas Marino\n    pdf-engine: weasyprint\ncss: cv.css\nformat-links: [pdf]\n---\n\n\n\n::: {.print-only .contact-block}\nnac.marino@gmail.com\n:::\n\n## Educação\n\n**Pós-doutorado em Ecologia -- Mudanças Climáticas e Interações Tróficas** <br> *Universidade Federal do Rio de Janeiro* [*Mar 2016 --- Jun 2019*]{.cvdate}\n\n-   Efeito das mudanças climáticas sobre as interações ecológicas  \n-   Bolsista do Programa Nacional de Pós-Doutorado (CAPES)  \n    \n**Doutor em Ecologia -- Mudanças Climáticas, Ecologia de Comunidades e Ecossistemas** <br> *Universidade Federal do Rio de Janeiro* [*Mar 2012 --- Fev 2016*]{.cvdate}\n\n-   O efeito de predadores na estrutura e funcionamento de cadeias traficas e sua interação com as mudanças climáticas\n-   Bolsista CAPES\n-   Melhor tese de Doutorado defendida no Programa de Pós-Graduação em Ecologia (UFRJ) em 2016  \n-   Período de doutorado-sanduíche na Univerdade da Columbia Britânica (Out 2014 - Mai 2015)\n    \n**Mestre em Ecologia -- Ecologia de Comunidades e Ecossistemas** <br> *Universidade Federal do Rio de Janeiro* [*Ago 2009 --- Jul 2011*]{.cvdate}\n\n-   Estruturação da comunidade de macroinvertebrados aquáticos em bromélias-tanque\n-   Bolsista CAPES\n\n**Bacharel em Ciências Biológicas -- Ecologia** <br> *Universidade Federal do Rio de Janeiro* [*Ago 2005 --- Jul 2009*]{.cvdate}\n\n-   Bromélias-tanque como ilhas: a influência das características do habitat sobre a riqueza de macroinvertebrados aquáticos\n-   Iniciação Científica - Bolsista FAPERJ  \n\n## Experiência{style=\"page-break-before: always\"}\n\n### Accenture\n\n***Data Science Principal*** [Jan 2021 -- Atual]{.cvdate}\n\nProviding data collection, pre-processing, exploratory analysis and modelling services to clients in the early R&D stages of developing data driven products. Projects include:\n\n-   Data description and preliminary product feasibility insights for a start-up real estate bond platform; including assessing suitability of various property transaction databases for use in initial product prototype.\n-   Development of statistical anomaly detection regimes and key historical insights from internet quality time-series data for use in parametric insurance products, including documenting analysis tools in an R package.\n\n***Data Science Consultant*** [Jul 2019 -- Dec 2020]{.cvdate}\n\n### Programa de Pós-Graduação em Ecologia (UFRJ)\n\n***Professor Visitante*** [Mar 2016 -- Jun 2019]{.cvdate}\n\n### Laboratório de Limnologia (UFRJ)\n\n***Pesquisador Associado*** [Mai 2006 -- Jun 2019]{.cvdate}\n\n***Projeto de Monitoramento dos Igarapés da FLONA Sacará-Taquera*** [Set 2009 -- Dec 2019]{.cvdate}\n\n***Projeto de Monitoramento das Lagoas Costeiras do Norte Fluminense*** [Jan 2007 -- Jun2010]{.cvdate}\n\n## Skills\n\n\n\n::: {.cell}\n::: {.cell-output .cell-output-stderr}\n```\nWarning: package 'ggplot2' was built under R version 4.3.2\n```\n:::\n\n::: {.cell-output-display}\n![](cv_files/figure-pdf/unnamed-chunk-1-1.pdf)\n:::\n:::\n\n\n\n## Tecnologias\n\n## Cursos\n\n## Licenças e Certificações\n\n::: {.no-print}\n## Apresentações\n\n-   Talk: [Misadventures with Reproducibility in R](https://github.com/cynthiahqy/rladies-2022-11) (30 Nov 2022, R Ladies Melbourne Meetup)\n-   Talk: [Designing R Packages](https://github.com/cynthiahqy/design-r-magic_2022-10) (4 Oct 2022, Monash EBS Data Science Research Software Study Group)\n-   Talk: [Quarto Websites as Research Compendiums](https://github.com/cynthiahqy/quarto-wiki-template) (16 Aug 2022, Monash EBS Data Science Research Software Study Group)\n-   Workshop: [Writing academic papers with Rmarkdown and friends](https://www.cynthiahqy.com/posts/r-markdown-and-friends/) (9 Aug 2022, Monash University)\n:::\n\n::: {.no-print}\n## Publicações\n\n-   Talk: [Misadventures with Reproducibility in R](https://github.com/cynthiahqy/rladies-2022-11) (30 Nov 2022, R Ladies Melbourne Meetup)\n-   Talk: [Designing R Packages](https://github.com/cynthiahqy/design-r-magic_2022-10) (4 Oct 2022, Monash EBS Data Science Research Software Study Group)\n-   Talk: [Quarto Websites as Research Compendiums](https://github.com/cynthiahqy/quarto-wiki-template) (16 Aug 2022, Monash EBS Data Science Research Software Study Group)\n-   Workshop: [Writing academic papers with Rmarkdown and friends](https://www.cynthiahqy.com/posts/r-markdown-and-friends/) (9 Aug 2022, Monash University)\n:::\n\n::: {.print-only}\n## References\nAvailable upon request\n:::\n",
    "supporting": [
      "cv_files\\figure-pdf"
    ],
    "filters": [
      "rmarkdown/pagebreak.lua"
    ],
    "includes": {},
    "engineDependencies": {},
    "preserve": null,
    "postProcess": false
  }
}